wavescapes/__init__.py
wavescapes/color.py
wavescapes/dft.py
wavescapes/draw.py
wavescapes/general.py
wavescapes/pcv.py
wavescapes/test_color.py
wavescapes-1.2.0.data/data/LICENSE
wavescapes-1.2.0.dist-info/LICENSE
wavescapes-1.2.0.dist-info/METADATA
wavescapes-1.2.0.dist-info/WHEEL
wavescapes-1.2.0.dist-info/top_level.txt
wavescapes-1.2.0.dist-info/RECORD
