Metadata-Version: 2.1
Name: wavescapes
Version: 1.2.0
Summary: Python library to build wavescapes, plots used in musicology.
Home-page: https://github.com/dcml/wavescapes
Author: Cédric Viaccoz
Author-email: cedric.viaccoz@gmail.com
License: UNKNOWN
Platform: UNKNOWN
Classifier: Programming Language :: Python :: 3
Classifier: License :: OSI Approved :: GNU General Public License v3 (GPLv3)
Classifier: Operating System :: OS Independent
Requires-Python: >=3.6
License-File: LICENSE
Requires-Dist: librosa
Requires-Dist: matplotlib
Requires-Dist: music21
Requires-Dist: numpy
Requires-Dist: pretty-midi
Requires-Dist: scipy
